src/reg_file.v
module reg_file (
    input clk,
    input rst,
    input [4:0] rs1,
    input [4:0] rs2,
    input [4:0] rd,
    input [31:0] wd,
    input reg_write,
    output [31:0] rd1,
    output [31:0] rd2
);
    reg [31:0] reg_mem [0:31];
    integer i;

    always @(posedge clk or posedge rst) begin
        if (rst)
            for (i = 0; i < 32; i = i + 1)
                reg_mem[i] <= 0;
        else if (reg_write)
            reg_mem[rd] <= wd;
    end

    assign rd1 = reg_mem[rs1];
    assign rd2 = reg_mem[rs2];
endmodule

src/instr_mem.v
module instr_mem (
    input [31:0] addr,
    output [31:0] instr
);
    reg [31:0] memory [0:255];

    initial begin
        $readmemh("mem/prog.mem", memory);
    end

    assign instr = memory[addr[9:2]];
endmodule

src/pc.v
module pc (
    input clk,
    input rst,
    output reg [31:0] pc_out
);
    always @(posedge clk or posedge rst) begin
        if (rst)
            pc_out <= 32'b0;
        else
            pc_out <= pc_out + 4;
    end
endmodule

tb/tb_cpu.v
`timescale 1ns / 1ps

module tb_cpu;

    // Clock and Reset
    reg clk = 0;
    reg rst = 1;

    // Wire declarations
    wire [31:0] pc;
    wire [31:0] instr;
    wire [31:0] rd1, rd2;

    // Instantiate Program Counter
    pc pc_inst (
        .clk(clk),
        .rst(rst),
        .pc_out(pc)
    );

    // Instantiate Instruction Memory
    instr_mem imem_inst (
        .addr(pc),
        .instr(instr)
    );

    // Instantiate Register File
    reg_file rf_inst (
        .clk(clk),
        .rst(rst),
        .rs1(5'd1),
        .rs2(5'd2),
        .rd(5'd3),
        .wd(32'hBEEFCAFE),
        .reg_write(1'b1),
        .rd1(rd1),
        .rd2(rd2)
    );

    // Clock generation
    always #5 clk = ~clk;

    // Initial simulation block
    initial begin
        $display("----- RISC-V CPU Day 2 Simulation Start -----");

        // Waveform output setup
        $dumpfile("waveforms/day2.vcd");
        $dumpvars(0, tb_cpu);

        // Monitor important values every time they change
        $monitor("Time=%0t | PC=%h | Instr=%h | RD1=%h | RD2=%h",
                  $time, pc, instr, rd1, rd2);

        // Release reset after 2 ns
        #2 rst = 0;

        // Run for 100 ns
        #100;

        $display("----- Simulation Complete -----");
        $finish;
    end

endmodule

waveforms/day2.vcd
$date
	Fri Jun 27 12:18:37 2025
$end
$version
	Icarus Verilog
$end
$timescale
	1ps
$end
$scope module tb_cpu $end
$var wire 32 ! rd2 [31:0] $end
$var wire 32 " rd1 [31:0] $end
$var wire 32 # pc [31:0] $end
$var wire 32 $ instr [31:0] $end
$var reg 1 % clk $end
$var reg 1 & rst $end
$scope module imem_inst $end
$var wire 32 ' instr [31:0] $end
$var wire 32 ( addr [31:0] $end
$upscope $end
$scope module pc_inst $end
$var wire 1 % clk $end
$var wire 1 & rst $end
$var reg 32 ) pc_out [31:0] $end
$upscope $end
$scope module rf_inst $end
$var wire 1 % clk $end
$var wire 5 * rd [4:0] $end
$var wire 32 + rd1 [31:0] $end
$var wire 32 , rd2 [31:0] $end
$var wire 1 - reg_write $end
$var wire 5 . rs1 [4:0] $end
$var wire 5 / rs2 [4:0] $end
$var wire 1 & rst $end
$var wire 32 0 wd [31:0] $end
$var integer 32 1 i [31:0] $end
$upscope $end
$upscope $end
$enddefinitions $end
$comment Show the parameter values. $end
$dumpall
$end
#0
$dumpvars
b100000 1
b10111110111011111100101011111110 0
b10 /
b1 .
1-
b0 ,
b0 +
b11 *
b0 )
b0 (
b10010011 '
1&
0%
b10010011 $
b0 #
b0 "
b0 !
$end
#2000
0&
#5000
b100010011 $
b100010011 '
b100 #
b100 (
b100 )
1%
#10000
0%
#15000
b110010011 $
b110010011 '
b1000 #
b1000 (
b1000 )
1%
#20000
0%
#25000
b1000010011 $
b1000010011 '
b1100 #
b1100 (
b1100 )
1%
#30000
0%
#35000
bx $
bx '
b10000 #
b10000 (
b10000 )
1%
#40000
0%
#45000
b10100 #
b10100 (
b10100 )
1%
#50000
0%
#55000
b11000 #
b11000 (
b11000 )
1%
#60000
0%
#65000
b11100 #
b11100 (
b11100 )
1%
#70000
0%
#75000
b100000 #
b100000 (
b100000 )
1%
#80000
0%
#85000
b100100 #
b100100 (
b100100 )
1%
#90000
0%
#95000
b101000 #
b101000 (
b101000 )
1%
