src/alu.v
module alu (
    input [31:0] a,
    input [31:0] b,
    input [3:0] alu_control,
    output reg [31:0] result
);
    always @(*) begin
        case (alu_control)
            4'b0000: result = a & b;
            4'b0001: result = a | b;
            4'b0010: result = a + b;
            4'b0110: result = a - b;
            default: result = 0;
        endcase
    end
endmodule

src/control.v
module control (
    input [6:0] opcode,
    output reg regWrite,
    output reg [3:0] alu_control
);
    always @(*) begin
        case (opcode)
            7'b0110011: begin // R-type
                regWrite = 1;
                alu_control = 4'b0010;
            end
            7'b0010011: begin // I-type (ADDI)
                regWrite = 1;
                alu_control = 4'b0010;
            end
            default: begin
                regWrite = 0;
                alu_control = 4'b0000;
            end
        endcase
    end
endmodule

src/reg_file.v
module reg_file (
    input clk,
    input rst,
    input [4:0] rs1,
    input [4:0] rs2,
    input [4:0] rd,
    input [31:0] wd,
    input reg_write,
    output [31:0] rd1,
    output [31:0] rd2
);
    reg [31:0] reg_mem [0:31];
    integer i;

    always @(posedge clk or posedge rst) begin
        if (rst)
            for (i = 0; i < 32; i = i + 1)
                reg_mem[i] <= 0;
        else if (reg_write)
            reg_mem[rd] <= wd;
    end

    assign rd1 = reg_mem[rs1];
    assign rd2 = reg_mem[rs2];
endmodule

src/instr_mem.v
module instr_mem (
    input [31:0] addr,
    output [31:0] instr
);
    reg [31:0] memory [0:255];

    initial begin
        $readmemh("mem/prog.mem", memory);
    end

    assign instr = memory[addr[9:2]];
endmodule

src/pc.v
module pc (
    input clk,
    input rst,
    output reg [31:0] pc_out
);
    always @(posedge clk or posedge rst) begin
        if (rst)
            pc_out <= 32'b0;
        else
            pc_out <= pc_out + 4;
    end
endmodule

src/cpu_core.v
module cpu_core (
    input clk,
    input rst
);
    wire [31:0] pc, instr;
    wire [31:0] reg_rd1, reg_rd2;
    wire [3:0] alu_ctrl;
    wire [31:0] alu_out;
    wire regWrite;

    pc pc_inst (.clk(clk), .rst(rst), .pc_out(pc));
    instr_mem imem (.addr(pc), .instr(instr));
    reg_file rf (
        .clk(clk), .rst(rst),
        .rs1(instr[19:15]), .rs2(instr[24:20]),
        .rd(instr[11:7]),
        .wd(alu_out),
        .reg_write(regWrite),
        .rd1(reg_rd1), .rd2(reg_rd2)
    );

    control control_inst (
        .opcode(instr[6:0]),
        .regWrite(regWrite),
        .alu_control(alu_ctrl)
    );

    alu alu_inst (
        .a(reg_rd1), .b(reg_rd2),
        .alu_control(alu_ctrl),
        .result(alu_out)
    );
endmodule

tb/tb_cpu.v
`timescale 1ns/1ps
module tb_cpu;

    reg clk = 0;
    reg rst = 1;

    // Instantiate CPU
    cpu_core core (
        .clk(clk),
        .rst(rst)
    );

    // Wire aliases to internal signals (so GTKWave can see them)
    wire [31:0] pc       = core.pc_inst.pc_out;
    wire [31:0] instr    = core.imem.instr;
    wire [31:0] alu_out  = core.alu_inst.result;
    wire        regWrite = core.control_inst.regWrite;

    always #5 clk = ~clk;

    initial begin
        $dumpfile("waveforms/fib.vcd");
        $dumpvars(0, tb_cpu); // Dumps all from tb_cpu

        $display("---- Fibonacci CPU Test Start ----");
        #2 rst = 0;
        #300;
        $display("---- Fibonacci CPU Test End ----");
        $finish;
    end

endmodule

waveforms/fib.vcd
$date
	Tue Jul  1 11:50:35 2025
$end
$version
	Icarus Verilog
$end
$timescale
	1ps
$end
$scope module tb_cpu $end
$var wire 32 ! alu_out [31:0] $end
$var wire 32 " instr [31:0] $end
$var wire 32 # pc [31:0] $end
$var wire 1 $ regWrite $end
$var reg 1 % clk $end
$var reg 1 & rst $end
$scope module core $end
$var wire 1 % clk $end
$var wire 1 & rst $end
$var wire 32 ' reg_rd2 [31:0] $end
$var wire 32 ( reg_rd1 [31:0] $end
$var wire 1 ) regWrite $end
$var wire 32 * pc [31:0] $end
$var wire 32 + instr [31:0] $end
$var wire 32 , alu_out [31:0] $end
$var wire 4 - alu_ctrl [3:0] $end
$scope module alu_inst $end
$var wire 32 . b [31:0] $end
$var wire 4 / alu_control [3:0] $end
$var wire 32 0 a [31:0] $end
$var reg 32 1 result [31:0] $end
$upscope $end
$scope module control_inst $end
$var wire 7 2 opcode [6:0] $end
$var reg 4 3 alu_control [3:0] $end
$var reg 1 ) regWrite $end
$upscope $end
$scope module imem $end
$var wire 32 4 instr [31:0] $end
$var wire 32 5 addr [31:0] $end
$upscope $end
$scope module pc_inst $end
$var wire 1 % clk $end
$var wire 1 & rst $end
$var reg 32 6 pc_out [31:0] $end
$upscope $end
$scope module rf $end
$var wire 1 % clk $end
$var wire 5 7 rd [4:0] $end
$var wire 32 8 rd1 [31:0] $end
$var wire 32 9 rd2 [31:0] $end
$var wire 1 ) reg_write $end
$var wire 5 : rs1 [4:0] $end
$var wire 5 ; rs2 [4:0] $end
$var wire 1 & rst $end
$var wire 32 < wd [31:0] $end
$var integer 32 = i [31:0] $end
$upscope $end
$upscope $end
$upscope $end
$enddefinitions $end
$comment Show the parameter values. $end
$dumpall
$end
#0
$dumpvars
b100000 =
b0 <
b0 ;
b0 :
b0 9
b0 8
b1 7
b0 6
b0 5
b10010011 4
b10 3
b10011 2
b0 1
b0 0
b10 /
b0 .
b10 -
b0 ,
b10010011 +
b0 *
1)
b0 (
b0 '
1&
0%
1$
b0 #
b10010011 "
b0 !
$end
#2000
0&
#5000
b10 7
b100010011 "
b100010011 +
b100010011 4
b100 #
b100 *
b100 5
b100 6
1%
#10000
0%
#15000
b11 7
b110010011 "
b110010011 +
b110010011 4
b1000 #
b1000 *
b1000 5
b1000 6
1%
#20000
0%
#25000
b100 7
b1000010011 "
b1000010011 +
b1000010011 4
b1100 #
b1100 *
b1100 5
b1100 6
1%
#30000
0%
#35000
b0 -
b0 /
b0 3
0$
0)
bx !
bx ,
bx 1
bx <
bx 2
bx 7
bx '
bx .
bx 9
bx ;
bx (
bx 0
bx 8
bx :
bx "
bx +
bx 4
b10000 #
b10000 *
b10000 5
b10000 6
1%
#40000
0%
#45000
b10100 #
b10100 *
b10100 5
b10100 6
1%
#50000
0%
#55000
b11000 #
b11000 *
b11000 5
b11000 6
1%
#60000
0%
#65000
b11100 #
b11100 *
b11100 5
b11100 6
1%
#70000
0%
#75000
b100000 #
b100000 *
b100000 5
b100000 6
1%
#80000
0%
#85000
b100100 #
b100100 *
b100100 5
b100100 6
1%
#90000
0%
#95000
b101000 #
b101000 *
b101000 5
b101000 6
1%
#100000
0%
#105000
b101100 #
b101100 *
b101100 5
b101100 6
1%
#110000
0%
#115000
b110000 #
b110000 *
b110000 5
b110000 6
1%
#120000
0%
#125000
b110100 #
b110100 *
b110100 5
b110100 6
1%
#130000
0%
#135000
b111000 #
b111000 *
b111000 5
b111000 6
1%
#140000
0%
#145000
b111100 #
b111100 *
b111100 5
b111100 6
1%
#150000
0%
#155000
b1000000 #
b1000000 *
b1000000 5
b1000000 6
1%
#160000
0%
#165000
b1000100 #
b1000100 *
b1000100 5
b1000100 6
1%
#170000
0%
#175000
b1001000 #
b1001000 *
b1001000 5
b1001000 6
1%
#180000
0%
#185000
b1001100 #
b1001100 *
b1001100 5
b1001100 6
1%
#190000
0%
#195000
b1010000 #
b1010000 *
b1010000 5
b1010000 6
1%
#200000
0%
#205000
b1010100 #
b1010100 *
b1010100 5
b1010100 6
1%
#210000
0%
#215000
b1011000 #
b1011000 *
b1011000 5
b1011000 6
1%
#220000
0%
#225000
b1011100 #
b1011100 *
b1011100 5
b1011100 6
1%
#230000
0%
#235000
b1100000 #
b1100000 *
b1100000 5
b1100000 6
1%
#240000
0%
#245000
b1100100 #
b1100100 *
b1100100 5
b1100100 6
1%
#250000
0%
#255000
b1101000 #
b1101000 *
b1101000 5
b1101000 6
1%
#260000
0%
#265000
b1101100 #
b1101100 *
b1101100 5
b1101100 6
1%
#270000
0%
#275000
b1110000 #
b1110000 *
b1110000 5
b1110000 6
1%
#280000
0%
#285000
b1110100 #
b1110100 *
b1110100 5
b1110100 6
1%
#290000
0%
#295000
b1111000 #
b1111000 *
b1111000 5
b1111000 6
1%
