src/pc.v
// pc.v - Program Counter

module pc (
    input clk,
    input reset,
    output reg [31:0] pc_out
);

    always @(posedge clk or posedge reset) begin
        if (reset)
            pc_out <= 0;
        else
            pc_out <= pc_out + 4;
    end

endmodule

tb/tb_pc.v
`timescale 1ns/1ps

module tb_pc;
    reg clk, reset;
    wire [31:0] pc_out;

    pc uut (
        .clk(clk),
        .reset(reset),
        .pc_out(pc_out)
    );

    initial begin
        $dumpfile("waveforms/pc.vcd");   // ✅ VCD output file
        $dumpvars;             // ✅ Dump all variables in this module

        clk = 0;
        reset = 1;
        #5 reset = 0;
        #100 $finish;
    end

    always #5 clk = ~clk;                // ✅ 10ns clock period

    initial begin
        $monitor("Time = %0t | PC = %h", $time, pc_out);  // ✅ Print to terminal
    end
endmodule

waveforms/pc.vcd
$date
	Thu Jun 26 12:18:41 2025
$end
$version
	Icarus Verilog
$end
$timescale
	1ps
$end
$scope module tb_pc $end
$var wire 32 ! pc_out [31:0] $end
$var reg 1 " clk $end
$var reg 1 # reset $end
$scope module uut $end
$var wire 1 " clk $end
$var wire 1 # reset $end
$var reg 32 $ pc_out [31:0] $end
$upscope $end
$upscope $end
$enddefinitions $end
$comment Show the parameter values. $end
$dumpall
$end
#0
$dumpvars
b0 $
1#
0"
b0 !
$end
#5000
b100 !
b100 $
1"
0#
#10000
0"
#15000
b1000 !
b1000 $
1"
#20000
0"
#25000
b1100 !
b1100 $
1"
#30000
0"
#35000
b10000 !
b10000 $
1"
#40000
0"
#45000
b10100 !
b10100 $
1"
#50000
0"
#55000
b11000 !
b11000 $
1"
#60000
0"
#65000
b11100 !
b11100 $
1"
#70000
0"
#75000
b100000 !
b100000 $
1"
#80000
0"
#85000
b100100 !
b100100 $
1"
#90000
0"
#95000
b101000 !
b101000 $
1"
#100000
0"
#105000
b101100 !
b101100 $
1"
